{
  "Edmonton Oilers VS Philadelphia Flyers": [
    {
      "1xbet": {
        "H1(-0.25)": 1.827
      }
    },
    {
      "22bet": {
        "2X": 1.97
      }
    },
    {
      "22bet": {
        "2": 3.32
      }
    },
    {
      "Percent Profit": "0.1529025422955641%"
    },
    {
      "Formula Type": "6"
    }
  ],
  "Sibir Novosibirsk VS Admiral Vladivostok": [
    {
      "22bet": {
        "H1(-1)": 2.48
      }
    },
    {
      "1xbet": {
        "H2(+1.5)": 1.55
      }
    },
    {
      "1xbet": {
        "H2(+0.75)": 1.866
      }
    },
    {
      "Percent Profit": "1.1793016973839343%"
    },
    {
      "Formula Type": "14"
    }
  ],
  "Eisbaren VS Dusseldorfer EG": [
    {
      "merrybet": {
        "Over(4.5)": 1.56
      }
    },
    {
      "sportybet": {
        "Under(4.5)": 2.9
      }
    },
    {
      "Percent Profit": "1.4146772767462465%"
    },
    {
      "Formula Type": "1"
    }
  ],
  "Schwenninger Wild Wings VS ERC Ingolstadt": [
    {
      "merrybet": {
        "Over(4.5)": 1.49
      }
    },
    {
      "sportybet": {
        "Under(4.5)": 3.2
      }
    },
    {
      "Percent Profit": "1.635906040268452%"
    },
    {
      "Formula Type": "1"
    }
  ],
  "Eisbaren Berlin - Dusseldorfer EG": [
    {
      "merrybet": {
        "Over(4.5)": 1.56
      }
    },
    {
      "sportybet": {
        "Under(4.5)": 2.9
      }
    },
    {
      "Percent Profit": "1.4146772767462465%"
    },
    {
      "Formula Type": "1"
    }
  ],
  "HK Avangard Omsk - Salavat Yulaev UFA": [
    {
      "merrybet": {
        "Over(4.5)": 1.67
      }
    },
    {
      "sportybet": {
        "Under(4.5)": 2.5
      }
    },
    {
      "Percent Profit": "0.11976047904191489%"
    },
    {
      "Formula Type": "1"
    }
  ],
  "Avtomobilist Yekaterinburg - Traktor Chelyabinsk": [
    {
      "merrybet": {
        "Over(4.5)": 1.86
      }
    },
    {
      "sportybet": {
        "Under(4.5)": 2.25
      }
    },
    {
      "Percent Profit": "1.7921146953405014%"
    },
    {
      "Formula Type": "1"
    }
  ],
  "Severstal Cherepovets - Amur Khabarovsk": [
    {
      "merrybet": {
        "Over(4.5)": 1.63
      }
    },
    {
      "sportybet": {
        "Under(4.5)": 2.7
      }
    },
    {
      "Percent Profit": "1.6132697114292256%"
    },
    {
      "Formula Type": "1"
    }
  ],
  "Neftekhimik Nizhnekamsk - HC Lada Togliatti": [
    {
      "merrybet": {
        "Over(4.5)": 1.71
      }
    },
    {
      "sportybet": {
        "Under(4.5)": 2.5
      }
    },
    {
      "Percent Profit": "1.5204678362573105%"
    },
    {
      "Formula Type": "1"
    }
  ],
  "Sibir Novosibirsk - Salavat Yulaev UFA": [
    {
      "merrybet": {
        "Over(4.5)": 1.87
      }
    },
    {
      "sportybet": {
        "Under(4.5)": 2.25
      }
    },
    {
      "Percent Profit": "2.0796197266785583%"
    },
    {
      "Formula Type": "1"
    }
  ],
  "SKA Saint Petersburg - Lokomotiv Yaroslavl": [
    {
      "merrybet": {
        "Over(4.5)": 1.75
      }
    },
    {
      "sportybet": {
        "Under(4.5)": 2.45
      }
    },
    {
      "Percent Profit": "2.040816326530617%"
    },
    {
      "Formula Type": "1"
    }
  ],
  "HC Dinamo Minsk - Amur Khabarovsk": [
    {
      "merrybet": {
        "Over(4.5)": 1.74
      }
    },
    {
      "sportybet": {
        "Under(4.5)": 2.45
      }
    },
    {
      "Percent Profit": "1.7124091015716658%"
    },
    {
      "Formula Type": "1"
    }
  ],
  "HK Chelny - Izhstal Izhevsk": [
    {
      "merrybet": {
        "Over(4.5)": 1.71
      }
    },
    {
      "sportybet": {
        "Under(4.5)": 2.5
      }
    },
    {
      "Percent Profit": "1.5204678362573105%"
    },
    {
      "Formula Type": "1"
    }
  ],
  "BK Mlada Boleslav - Ocelari Trinec": [
    {
      "merrybet": {
        "Over(4.5)": 1.7
      }
    },
    {
      "sportybet": {
        "Under(4.5)": 2.5
      }
    },
    {
      "Percent Profit": "1.17647058823529%"
    },
    {
      "Formula Type": "1"
    }
  ],
  "HC Plzen - HC Olomouc": [
    {
      "merrybet": {
        "Over(4.5)": 1.83
      }
    },
    {
      "sportybet": {
        "Under(4.5)": 2.3
      }
    },
    {
      "Percent Profit": "1.8769303872653893%"
    },
    {
      "Formula Type": "1"
    }
  ],
  "Red Bull Munich - Adler Mannheim": [
    {
      "merrybet": {
        "Over(4.5)": 1.58
      }
    },
    {
      "sportybet": {
        "Under(4.5)": 2.85
      }
    },
    {
      "Percent Profit": "1.6211414612480723%"
    },
    {
      "Formula Type": "1"
    }
  ],
  "Wild Wings - ERC Ingolstadt": [
    {
      "merrybet": {
        "Over(4.5)": 1.49
      }
    },
    {
      "sportybet": {
        "Under(4.5)": 3.2
      }
    },
    {
      "Percent Profit": "1.635906040268452%"
    },
    {
      "Formula Type": "1"
    }
  ],
  "BK Mlada Boleslav - HC Ocelari Trinec": [
    {
      "merrybet": {
        "Over(4.5)": 1.7
      }
    },
    {
      "sportybet": {
        "Under(4.5)": 2.5
      }
    },
    {
      "Percent Profit": "1.17647058823529%"
    },
    {
      "Formula Type": "1"
    }
  ],
  "EHC Red Bull M\u00fcnchen - Adler Mannheim": [
    {
      "merrybet": {
        "Over(4.5)": 1.58
      }
    },
    {
      "sportybet": {
        "Under(4.5)": 2.85
      }
    },
    {
      "Percent Profit": "1.6211414612480723%"
    },
    {
      "Formula Type": "1"
    }
  ],
  "HK Avangard Omsk - Salavat Yulaev Ufa": [
    {
      "merrybet": {
        "Over(4.5)": 1.67
      }
    },
    {
      "sportybet": {
        "Under(4.5)": 2.5
      }
    },
    {
      "Percent Profit": "0.11976047904191489%"
    },
    {
      "Formula Type": "1"
    }
  ],
  "Avtomobilist Yekaterinburg - HC Traktor Chelyabinsk": [
    {
      "merrybet": {
        "Over(4.5)": 1.86
      }
    },
    {
      "sportybet": {
        "Under(4.5)": 2.25
      }
    },
    {
      "Percent Profit": "1.7921146953405014%"
    },
    {
      "Formula Type": "1"
    }
  ],
  "Severstal Cherepovec - Amur Khabarovsk": [
    {
      "merrybet": {
        "Over(4.5)": 1.63
      }
    },
    {
      "sportybet": {
        "Under(4.5)": 2.7
      }
    },
    {
      "Percent Profit": "1.6132697114292256%"
    },
    {
      "Formula Type": "1"
    }
  ],
  "Sibir Novosibirsk - Salavat Yulaev Ufa": [
    {
      "merrybet": {
        "Over(4.5)": 1.87
      }
    },
    {
      "sportybet": {
        "Under(4.5)": 2.25
      }
    },
    {
      "Percent Profit": "2.0796197266785583%"
    },
    {
      "Formula Type": "1"
    }
  ],
  "SKA St. Petersburg - Lokomotiv Yaroslavl": [
    {
      "merrybet": {
        "Over(4.5)": 1.75
      }
    },
    {
      "sportybet": {
        "Under(4.5)": 2.45
      }
    },
    {
      "Percent Profit": "2.040816326530617%"
    },
    {
      "Formula Type": "1"
    }
  ]
}